odoo/addons/shopfloor_reception_measuring_device/README.rst
odoo/addons/shopfloor_reception_measuring_device/__init__.py
odoo/addons/shopfloor_reception_measuring_device/__manifest__.py
odoo/addons/shopfloor_reception_measuring_device/actions/__init__.py
odoo/addons/shopfloor_reception_measuring_device/actions/messages.py
odoo/addons/shopfloor_reception_measuring_device/i18n/it.po
odoo/addons/shopfloor_reception_measuring_device/i18n/shopfloor_reception_measuring_device.pot
odoo/addons/shopfloor_reception_measuring_device/readme/CONTRIBUTORS.md
odoo/addons/shopfloor_reception_measuring_device/readme/DESCRIPTION.md
odoo/addons/shopfloor_reception_measuring_device/services/__init__.py
odoo/addons/shopfloor_reception_measuring_device/services/reception.py
odoo/addons/shopfloor_reception_measuring_device/static/description/icon.png
odoo/addons/shopfloor_reception_measuring_device/static/description/index.html
odoo/addons/shopfloor_reception_measuring_device/tests/__init__.py
odoo/addons/shopfloor_reception_measuring_device/tests/device_component.py
odoo/addons/shopfloor_reception_measuring_device/tests/device_model.py
odoo/addons/shopfloor_reception_measuring_device/tests/test_reception_measuring_device.py
odoo_addon_shopfloor_reception_measuring_device-18.0.1.1.0.2.dist-info/METADATA
odoo_addon_shopfloor_reception_measuring_device-18.0.1.1.0.2.dist-info/WHEEL
odoo_addon_shopfloor_reception_measuring_device-18.0.1.1.0.2.dist-info/top_level.txt
odoo_addon_shopfloor_reception_measuring_device-18.0.1.1.0.2.dist-info/RECORD
